{"about":{"name":"CryptoPeep #8249","artist":"Benzega","description":"One-of-a-kind pop art pixel peep living on the blockchain!","links":{"homepage":"cryptopeeps.io","github":"github.com/cryptopeeps","reddit":"reddit.com/r/cryptopeeps","artist":"benzega.com"},"properties":{"background":"Purple","species":"Human","variant":"Normal","clothing":"Tank Top","logo":"Smiley Face","hair":"Pigtails","items":["Flag of America"],"expression":"Grin","eyebrows":"Natural","eyes":"Glance"}},"files":[{"proximity":"on-chain","media_type":"image/svg+xml","src":{"chunks":{"0":"<svg xmlns=\"http://www.w3.org/2000/svg\" viewBox=\"0 0 29 33\"><def","1":"s><style>polygon,rect,path{shape-rendering:crispedges;}.ca13-1{f","2":"ill:#6b4f99;}.ca13-2{fill:#000000;}.ca13-3{fill:#b2622b;}.ca13-4","3":"{fill:#c6e5e4;}.ca13-5{fill:#508e91;}.ca13-6{fill:#ffffff;}.ca13","4":"-7{fill:#5e362f;}.ca13-8{fill:#ffa9d0;}.ca13-9{fill:#455054;}.ca","5":"13-10{fill:#ff1f4a;}.ca13-11{fill:#ffffff;}.ca13-12{fill:#0068ff","6":";}</style></defs><rect class=\"ca13-1\" x=\"8\" y=\"21\" width=\"1\" hei","7":"ght=\"1\"/><path class=\"ca13-1\" d=\"M9,19V17H8v3H9Z\"/><path class=\"","8":"ca13-1\" d=\"M8,32H6V31H5V22H6V21H7V20H5v1H2V17H5V16H8V12H9V10h1V9","9":"h1V8h7V9h1v1h1v2h1v6H20v2h1v1H20v1H19V21H17v3h2v1h2v1h1v1h1v6h6V","10":"0H0V33H8Z\"/><path class=\"ca13-1\" d=\"M11,24h1V21H10v1H9v2H8v1h2V2","11":"4Z\"/><path class=\"ca13-2\" d=\"M23,27H22v6h1V27Z\"/><rect class=\"ca","12":"13-2\" x=\"21\" y=\"26\" width=\"1\" height=\"1\"/><path class=\"ca13-3\" d","13":"=\"M22,27H21v6h1V27Z\"/><rect class=\"ca13-3\" x=\"20\" y=\"26\" width=\"","14":"1\" height=\"1\"/><path class=\"ca13-2\" d=\"M21,27H20v6h1V27Z\"/><path","15":" class=\"ca13-2\" d=\"M20,26h1V25H19v1Z\"/><path class=\"ca13-4\" d=\"M","16":"20,27V26H19V25H18v1H17v1H16v1h1v1h1v1h1v3h1V27Z\"/><rect class=\"c","17":"a13-4\" x=\"12\" y=\"30\" width=\"1\" height=\"1\"/><rect class=\"ca13-4\" ","18":"x=\"16\" y=\"30\" width=\"1\" height=\"1\"/><path class=\"ca13-4\" d=\"M10,","19":"30h1V29h1V28h1V27H12V26H11V25H10v1H9v7h1V30Z\"/><path class=\"ca13","20":"-4\" d=\"M16,32H12v1h5V32Z\"/><path class=\"ca13-2\" d=\"M18,26V25h1V2","21":"4H17v2Z\"/><rect class=\"ca13-2\" x=\"16\" y=\"26\" width=\"1\" height=\"1","22":"\"/><path class=\"ca13-2\" d=\"M13,27v1h3V27H13Z\"/><path class=\"ca13","23":"-3\" d=\"M16,23H13v1H12v2h1v1h3V26h1V24H16Z\"/><rect class=\"ca13-2\"","24":" x=\"12\" y=\"26\" width=\"1\" height=\"1\"/><path class=\"ca13-2\" d=\"M11","25":",24H10v1h1v1h1V24Z\"/><path class=\"ca13-3\" d=\"M8,27H9V26H8Z\"/><pa","26":"th class=\"ca13-2\" d=\"M9,27H8V26h2V25H8V24H7v7H6v1H8v1H9V27Z\"/><p","27":"ath class=\"ca13-3\" d=\"M7,30V24H8V22H6v9H7Z\"/><path class=\"ca13-2","28":"\" d=\"M6,22H5v9H6V22Z\"/><path class=\"ca13-5\" d=\"M19,30H18V29H17V2","29":"8H12v1H11v1H10v3h2V32h5v1h2V30Zm-6,1H12V30h1Zm4,0H16V30h1Z\"/><pa","30":"th class=\"ca13-3\" d=\"M18,20V19h1V16h1V15H16V14h2V13H16V12h1V11H1","31":"6V10H15v1H14v1H13v3H10v4h1v1h1v1h1v1h3V21h1V20Zm-4-4h1v1H14Zm2,3","32":"v1H13V19h3V18h1v1Z\"/><path class=\"ca13-2\" d=\"M19,16v3h1V16Z\"/><r","33":"ect class=\"ca13-2\" x=\"18\" y=\"19\" width=\"1\" height=\"1\"/><path cla","34":"ss=\"ca13-2\" d=\"M17,20v1h1V20Z\"/><path class=\"ca13-2\" d=\"M16,22H1","35":"3V21H12v3h1V23h3v1h1V21H16Z\"/><path class=\"ca13-2\" d=\"M12,21V20H","36":"11v1Z\"/><rect class=\"ca13-2\" x=\"10\" y=\"19\" width=\"1\" height=\"1\"/","37":"><path class=\"ca13-2\" d=\"M10,19V18H9v1Z\"/><rect class=\"ca13-2\" x","38":"=\"14\" y=\"16\" width=\"1\" height=\"1\"/><path class=\"ca13-6\" d=\"M18,1","39":"5h1V14H18Z\"/><path class=\"ca13-6\" d=\"M13,15V14H12v1Z\"/><path cla","40":"ss=\"ca13-2\" d=\"M17,14H16v1h2V14Z\"/><path class=\"ca13-2\" d=\"M12,1","41":"4H10v1h2Z\"/><rect class=\"ca13-7\" x=\"18\" y=\"13\" width=\"1\" height=","42":"\"1\"/><path class=\"ca13-7\" d=\"M16,13h2V12H16Z\"/><path class=\"ca13","43":"-7\" d=\"M13,13H12v1h1Z\"/><rect class=\"ca13-2\" x=\"13\" y=\"19\" width","44":"=\"3\" height=\"1\"/><rect class=\"ca13-2\" x=\"16\" y=\"18\" width=\"1\" he","45":"ight=\"1\"/><path class=\"ca13-8\" d=\"M19,20H18v1h1v1h1V21h1V20H20V1","46":"9H19Z\"/><path class=\"ca13-8\" d=\"M9,22h1V21h1V20H10V19H9v1H8v1H9Z","47":"\"/><path class=\"ca13-8\" d=\"M9,17v1h1V14h2V13h1V12h1V11h1V10h1v1h","48":"1v1h1v1h1v2h1v3h1V12H20V10H19V9H18V8H11V9H10v1H9v2H8v5Z\"/><path ","49":"class=\"ca13-9\" d=\"M8,22V20H7v2Z\"/><path class=\"ca13-10\" d=\"M5,17","50":"H2v1H5Z\"/><path class=\"ca13-10\" d=\"M2,19v1H5V19Z\"/><path class=\"","51":"ca13-11\" d=\"M2,21H5V20H2Z\"/><path class=\"ca13-12\" d=\"M6,18H8V16H","52":"5v2Z\"/><path class=\"ca13-11\" d=\"M5,18H2v1H5Z\"/><path class=\"ca13","53":"-10\" d=\"M7,18H5v1H8V18Z\"/><path class=\"ca13-11\" d=\"M8,19H5v1H8Z\"","54":"/><path class=\"ca13-2\" d=\"M7,21H6v1H7Z\"/><path class=\"ca13-2\" d=","55":"\"M9,22H8v2H9Z\"/></svg>"}}}]}