{"about":{"name":"CryptoPeep #3985","artist":"Benzega","description":"One-of-a-kind pop art pixel peep living on the blockchain!","links":{"homepage":"cryptopeeps.io","github":"github.com/cryptopeeps","reddit":"reddit.com/r/cryptopeeps","artist":"benzega.com"},"properties":{"background":"Chartreuse","species":"Human","variant":"Normal","clothing":"Leather Jacket","hair":"Crew Cut","facial_hair":"Beard","eyewear":"Sunglasses","expression":"Grin","eyebrows":"Natural","eyes":"Center"}},"files":[{"proximity":"on-chain","media_type":"image/svg+xml","src":{"chunks":{"0":"<svg xmlns=\"http://www.w3.org/2000/svg\" viewBox=\"0 0 29 33\"><def","1":"s><style>polygon,rect,path{shape-rendering:crispedges;}.fb283-1{","2":"fill:#b4bd09;}.fb283-2{fill:#000000;}.fb283-3{fill:#66334f;}.fb2","3":"83-4{fill:#ffffff;}.fb283-5{fill:#e8b795;}.fb283-6{fill:#90a2a3;","4":"}.fb283-7{fill:#8e4717;}.fb283-8{fill:#8e4717;}.fb283-9{fill:#ff","5":"1f4a;}.fb283-10{fill:#cbed03;}.fb283-11{fill:#00e070;}</style></","6":"defs><path class=\"fb283-1\" d=\"M0,33H6V27H7V26H8V25H9V24h1V23h1V2","7":"1H10V20H9V16H8V14H9V10h1V9h1V8h7V9h1v1h1v4h1v2H20v4H19v1H18v2h1v","8":"1h1v1h1v1h1v1h1v6h6V0H0Z\"/><path class=\"fb283-2\" d=\"M23,27H22v6h","9":"1V27Z\"/><path class=\"fb283-3\" d=\"M22,27H21v6h1V27Z\"/><path class","10":"=\"fb283-2\" d=\"M21,27h1V26H21V25H20v2H17v1h2v1h1v4h1V27Z\"/><rect ","11":"class=\"fb283-2\" x=\"19\" y=\"24\" width=\"1\" height=\"1\"/><path class=","12":"\"fb283-3\" d=\"M20,29H19v1H18v1H17v1H16v1h4V29Z\"/><rect class=\"fb2","13":"83-2\" x=\"18\" y=\"23\" width=\"1\" height=\"1\"/><path class=\"fb283-3\" ","14":"d=\"M18,25H17v1H16v5h1V30h1V29h1V28H17V27h2V26h1V25H19V24H18Z\"/><","15":"rect class=\"fb283-3\" x=\"17\" y=\"23\" width=\"1\" height=\"1\"/><rect c","16":"lass=\"fb283-2\" x=\"17\" y=\"24\" width=\"1\" height=\"1\"/><rect class=\"","17":"fb283-2\" x=\"18\" y=\"29\" width=\"1\" height=\"1\"/><rect class=\"fb283-","18":"2\" x=\"16\" y=\"25\" width=\"1\" height=\"1\"/><path class=\"fb283-4\" d=\"","19":"M15,27H14v6h1V27Z\"/><path class=\"fb283-2\" d=\"M12,24h1V22H11v1h1Z","20":"\"/><path class=\"fb283-5\" d=\"M17,25V24H16V23H13v1H12v1h1v1h3V25Z\"","21":"/><rect class=\"fb283-2\" x=\"12\" y=\"25\" width=\"1\" height=\"1\"/><pat","22":"h class=\"fb283-3\" d=\"M12,32V31H11V30H10V29H9v4h4V32Z\"/><rect cla","23":"ss=\"fb283-3\" x=\"11\" y=\"23\" width=\"1\" height=\"1\"/><rect class=\"fb","24":"283-2\" x=\"11\" y=\"24\" width=\"1\" height=\"1\"/><rect class=\"fb283-2\"","25":" x=\"11\" y=\"30\" width=\"1\" height=\"1\"/><rect class=\"fb283-2\" x=\"10","26":"\" y=\"23\" width=\"1\" height=\"1\"/><rect class=\"fb283-2\" x=\"9\" y=\"24","27":"\" width=\"1\" height=\"1\"/><path class=\"fb283-3\" d=\"M10,26v1h2v1H10","28":"v1h1v1h1v1h1V26H12V25H11V24H10v1H9v1Z\"/><path class=\"fb283-2\" d=","29":"\"M9,29h1V28h2V27H9V25H8v1H7v1H8v6H9V29Z\"/><path class=\"fb283-3\" ","30":"d=\"M8,27H7v6H8V27Z\"/><path class=\"fb283-2\" d=\"M7,27H6v6H7V27Z\"/>","31":"<rect class=\"fb283-2\" x=\"10\" y=\"29\" width=\"1\" height=\"1\"/><rect ","32":"class=\"fb283-2\" x=\"17\" y=\"30\" width=\"1\" height=\"1\"/><path class=","33":"\"fb283-2\" d=\"M17,32V31H16V26H13v5H12v1h1v1h1V27h1v6h1V32Z\"/><pat","34":"h class=\"fb283-6\" d=\"M9,26v1h1V26Z\"/><path class=\"fb283-6\" d=\"M1","35":"9,27h1V26H19Z\"/><path class=\"fb283-2\" d=\"M20,16h1V15H20Z\"/><rect","36":" class=\"fb283-5\" x=\"14\" y=\"15\" width=\"1\" height=\"1\"/><rect class","37":"=\"fb283-5\" x=\"13\" y=\"20\" width=\"1\" height=\"1\"/><rect class=\"fb28","38":"3-5\" x=\"10\" y=\"12\" width=\"1\" height=\"1\"/><path class=\"fb283-5\" d","39":"=\"M13,13v1h3V13h1V12h1V11H17V10H12v1H11v1h2Z\"/><rect class=\"fb28","40":"3-5\" x=\"15\" y=\"20\" width=\"1\" height=\"1\"/><path class=\"fb283-5\" d","41":"=\"M16,17V16H15v1H14V16H13v1H10v1h1v1h1V18h2v1h1V18h2v1h1V18h1V17","42":"H16Z\"/><path class=\"fb283-2\" d=\"M16,23v1h1V23h1V22H16Z\"/><path c","43":"lass=\"fb283-2\" d=\"M8,15v1H9V15Z\"/><rect class=\"fb283-2\" x=\"14\" y","44":"=\"16\" width=\"1\" height=\"1\"/><polygon class=\"fb283-7\" points=\"12 ","45":"13 13 13 13 12 11 12 11 13 12 13\"/><path class=\"fb283-7\" d=\"M17,","46":"13h2V12H17Z\"/><path class=\"fb283-8\" d=\"M14,18H13v1h1Z\"/><path cl","47":"ass=\"fb283-8\" d=\"M13,23h3V22h2V21h1V20h1V16H19v2H18v1H17V18H15v1","48":"h1v2H15V20H14v1H13V19H11V18H10V16H9v4h1v1h1v1h2Z\"/><path class=\"","49":"fb283-2\" d=\"M13,19v1h3V19H13Z\"/><path class=\"fb283-2\" d=\"M12,18v","50":"1h1V18Z\"/><path class=\"fb283-9\" d=\"M10,13V12h1V11h1V10h5v1h1v1h1","51":"v2h1V10H19V9H18V8H11V9H10v1H9v4h1Z\"/><path class=\"fb283-10\" d=\"M","52":"19,15v1h1V15h1V14H19Z\"/><path class=\"fb283-10\" d=\"M16,13v1h3V13H","53":"16Z\"/><path class=\"fb283-11\" d=\"M19,14H16v2h3V14Z\"/><path class=","54":"\"fb283-10\" d=\"M16,16v1h3V16H16Z\"/><path class=\"fb283-10\" d=\"M13,","55":"14v2h1V15h1v1h1V14H13Z\"/><path class=\"fb283-10\" d=\"M13,14V13H10v","56":"1h3Z\"/><path class=\"fb283-11\" d=\"M13,16V14H10v2h3Z\"/><path class","57":"=\"fb283-10\" d=\"M13,17V16H10v1h3Z\"/><path class=\"fb283-10\" d=\"M10","58":",15V14H8v1H9v1h1Z\"/></svg>"}}}]}