{"name":"CryptoPeep #3839","artist":"Benzega","description":"One-of-a-kind pop art pixel peep living on the blockchain!","homepage":"https://www.cryptopeeps.io","Properties":{"Background":"Orange","Species":"Human","Variant":"Normal","Clothing":"Tank Top","Logo":"ADA","Hair":"Frizzy","Facial Hair":"Mustache","Items":"Dinosaur Puppet","Expression":"Neutral","Eyebrows":"Natural","Eyes":"Glance"},"image":["data:image/svg+xml;utf8,%3Csvg xmlns='http://www.w3.org/2000/svg","' xmlns:xlink='http://www.w3.org/1999/xlink' viewBox='0 0 29 33'","%3E%3Cdefs%3E%3Cstyle%3Epolygon,rect,path%7Bshape-rendering:cris","pedges;%7D.ba26-1%7Bfill:%23e55b35;%7D.ba26-2%7Bfill:%23000000;%","7D.ba26-3%7Bfill:%23e8b795;%7D.ba26-4%7Bfill:%23508e5d;%7D.ba26-","5%7Bfill:%23c5e2d0;%7D.ba26-6%7Bfill:%23ffffff;%7D.ba26-7%7Bfill",":%238e703c;%7D.ba26-8%7Bfill:%235a2de2;%7D.ba26-9%7Bfill:%2300af","68;%7D.ba26-10%7Bfill:%23fad000;%7D.ba26-11%7Bfill:%236d5800;%7D",".ba26-12%7Bfill:%239b8100;%7D.ba26-13%7Bfill:%23ffffff;%7D.ba26-","14%7Bfill:%23e70059;%7D%3C/style%3E%3C/defs%3E%3Cpath class='ba2","6-1' d='M20,23V19H19v1H18v1H17v3h2v1h2V23Z'/%3E%3Crect class='ba","26-1' x='20' y='17' width='1' height='1'/%3E%3Cpath class='ba26-","1' d='M0,33H6V27H7V26H8V25h2V24h2V21H11V20H10V19H9V17H8V15H7V14H","9V13H7V12H9V11H8V9H9v1h2V9H10V8H9V7h1V8h1V7h1V8h1V7h2V8h1V7h1V8h","1V9h1V8h2V9H20v2h1V10h1v2H21v2h1v1H21v2h1V16h1v1h1v1h1v5H24v8H23","v1H21v1h8V0H0Z'/%3E%3Cpath class='ba26-2' d='M7,27H6v6H7V27Z'/%3","E%3Crect class='ba26-2' x='7' y='26' width='1' height='1'/%3E%3C","path class='ba26-3' d='M8,27H7v6H8V27Z'/%3E%3Crect class='ba26-3","' x='8' y='26' width='1' height='1'/%3E%3Cpath class='ba26-2' d=","'M9,30V27H8v6H9V30Z'/%3E%3Cpath class='ba26-2' d='M10,26V25H8v1h","2Z'/%3E%3Crect class='ba26-4' x='10' y='32' width='1' height='1'","/%3E%3Crect class='ba26-4' x='18' y='32' width='1' height='1'/%3","E%3Cpath class='ba26-4' d='M17,30h1V29h1v1h1V26H19V25H18v1H17v1H","16v1H13V27H12V26H11V25H10v1H9v4h1V29h1v1h1v3h1V29h2v1h1v2H15v1h2","V30Z'/%3E%3Crect class='ba26-4' x='18' y='30' width='1' height='","1'/%3E%3Cpath class='ba26-4' d='M14,31v1h1V30H14Z'/%3E%3Crect cl","ass='ba26-4' x='10' y='30' width='1' height='1'/%3E%3Cpath class","='ba26-2' d='M11,26h1V24H10v1h1Z'/%3E%3Cpath class='ba26-2' d='M","13,23h3v1h1V21H16v1H13V21H12v3h1Z'/%3E%3Crect class='ba26-2' x='","12' y='26' width='1' height='1'/%3E%3Cpath class='ba26-2' d='M13",",27v1h3V27H13Z'/%3E%3Cpath class='ba26-3' d='M13,26v1h3V26h1V24H","16V23H13v1H12v2Z'/%3E%3Crect class='ba26-2' x='16' y='26' width=","'1' height='1'/%3E%3Cpath class='ba26-2' d='M18,24H17v2h1V25h1V2","4Z'/%3E%3Cpath class='ba26-3' d='M21,27V26H20v1Z'/%3E%3Cpath cla","ss='ba26-2' d='M22,32h1V31H22V25H19v1h2v1H20v6h1V32Z'/%3E%3Cpath"," class='ba26-3' d='M23,26V25H22v6h1V26Z'/%3E%3Cpath class='ba26-","2' d='M23,26v5h1V25H23Z'/%3E%3Cpath class='ba26-5' d='M20,30H19v","1H18V30H17v3h1V32h1v1h1V30Z'/%3E%3Crect class='ba26-5' x='18' y=","'29' width='1' height='1'/%3E%3Cpath class='ba26-5' d='M16,32V30","H15v2Z'/%3E%3Cpath class='ba26-5' d='M14,32V30h1V29H13v4h2V32Z'/","%3E%3Cpath class='ba26-5' d='M12,30H11v1H10V30H9v3h1V32h1v1h1V30","Z'/%3E%3Crect class='ba26-5' x='10' y='29' width='1' height='1'/","%3E%3Crect class='ba26-2' x='19' y='13' width='1' height='1'/%3E","%3Crect class='ba26-3' x='16' y='12' width='1' height='1'/%3E%3C","rect class='ba26-3' x='13' y='10' width='1' height='1'/%3E%3Cpat","h class='ba26-3' d='M13,22h3V21h1V20h1V19h1V16h1V15H16V13H15V12H","13v1H11v1h2v1H9v1h1v3h1v1h1v1h1Zm1-6h1v1H14Zm-2,3V18h5v1H16v1H13","V19Z'/%3E%3Crect class='ba26-3' x='17' y='11' width='1' height='","1'/%3E%3Cpath class='ba26-2' d='M20,18V16H19v3h1Z'/%3E%3Crect cl","ass='ba26-2' x='18' y='19' width='1' height='1'/%3E%3Crect class","='ba26-2' x='17' y='20' width='1' height='1'/%3E%3Crect class='b","a26-2' x='11' y='20' width='1' height='1'/%3E%3Crect class='ba26","-2' x='10' y='19' width='1' height='1'/%3E%3Cpath class='ba26-2'"," d='M10,16H9v3h1V16Z'/%3E%3Crect class='ba26-2' x='14' y='16' wi","dth='1' height='1'/%3E%3Cpath class='ba26-6' d='M10,15h1V14H10Z'","/%3E%3Cpath class='ba26-6' d='M16,14v1h1V14Z'/%3E%3Cpath class='","ba26-2' d='M12,15h1V14H11v1Z'/%3E%3Cpath class='ba26-2' d='M18,1","4H17v1h2V14Z'/%3E%3Crect class='ba26-7' x='10' y='13' width='1' ","height='1'/%3E%3Cpath class='ba26-7' d='M12,13h1V12H12Z'/%3E%3Cp","ath class='ba26-7' d='M17,13H16v1h1Z'/%3E%3Crect class='ba26-7' ","x='17' y='12' width='1' height='1'/%3E%3Cpath class='ba26-8' d='","M16,19h1V18H12v1h4Z'/%3E%3Cpath class='ba26-2' d='M13,20h3V19H13","Z'/%3E%3Cpath class='ba26-9' d='M9,15h1V13h2V12h3v1h1V12h1V11h1v","2H17v1h2V13h1v1H19v1h1v2h1V15h1V14H21V12h1V10H21v1H20V9h1V8H19V9","H18V8H17V7H16V8H15V7H13V8H12V7H11V8H10V9h1v1H9V9H8v2H9v1H7v1H9v1","H7v1H8v2H9V15Zm4-5h1v1H13Z'/%3E%3Crect class='ba26-9' x='9' y='7","' width='1' height='1'/%3E%3Cpath class='ba26-10' d='M23,20V18H2","2v2H21V18H20v3h5V18H24v2Z'/%3E%3Cpath class='ba26-2' d='M22,20V1","8H21v2Z'/%3E%3Cpath class='ba26-2' d='M23,19v1h1V18H23Z'/%3E%3Cp","ath class='ba26-11' d='M22,23H21v2h3V23H22Z'/%3E%3Cpath class='b","a26-12' d='M21,23V21H20v2Z'/%3E%3Cpath class='ba26-12' d='M24,21",".222V23h1V21H24Z'/%3E%3Cpath class='ba26-2' d='M23,22V21H22v1Z'/","%3E%3Cpath class='ba26-13' d='M22,22V21H21v1Z'/%3E%3Cpath class=","'ba26-13' d='M24,22V21H23v1Z'/%3E%3Crect class='ba26-10' x='21' ","y='17' width='1' height='1'/%3E%3Crect class='ba26-10' x='23' y=","'17' width='1' height='1'/%3E%3Cpolygon class='ba26-12' points='","23 18 23 17 23 16 22 16 22 17 22 18 23 18'/%3E%3Cpath class='ba2","6-14' d='M22,23h1V22H22Z'/%3E%3Cpath class='ba26-2' d='M21,22v1h","1V22Z'/%3E%3Cpath class='ba26-2' d='M23,22v1h1V22Z'/%3E%3C/svg%3","E"],"mediaType":"image/svg+xml"}