{"about":{"name":"CryptoPeep #4477","artist":"Benzega","description":"One-of-a-kind pop art pixel peep living on the blockchain!","links":{"homepage":"cryptopeeps.io","github":"github.com/cryptopeeps","reddit":"reddit.com/r/cryptopeeps","artist":"benzega.com"},"properties":{"background":"Red","species":"Human","variant":"Normal","clothing":"Turtleneck","pattern":"Stripes","hair":"Afro","facial_hair":"Lumberjack","expression":"Grin","eyebrows":"Inquisitive","eyes":"Center"}},"files":[{"proximity":"on-chain","media_type":"image/svg+xml","src":["<svg xmlns=\"http://www.w3.org/2000/svg\" viewBox=\"0 0 29 33\"><def","s><style>polygon,rect,path{shape-rendering:crispedges;}.ka139-1{","fill:#d14646;}.ka139-2{fill:#000000;}.ka139-3{fill:#a0688d;}.ka1","39-4{fill:#66334f;}.ka139-5{fill:#ce8452;}.ka139-6{fill:#ffffff;","}.ka139-7{fill:#6f7032;}.ka139-8{fill:#6f7032;}.ka139-9{fill:#ff","791f;}</style></defs><path class=\"ka139-1\" d=\"M0,33H6V27H7V26H8V","25h2V24h2V22H11V21H10V20H9V16H8V15H9V13H8V9H9V8h1V7h1V6h7V7h1V8h","1V9h1v4H20v2h1v1H20v4H19v1H18v1H17v2h2v1h2v1h1v1h1v6h6V0H0Z\"/><p","ath class=\"ka139-2\" d=\"M23,27H22v6h1V27Z\"/><rect class=\"ka139-2\""," x=\"21\" y=\"26\" width=\"1\" height=\"1\"/><path class=\"ka139-3\" d=\"M2","1,28h1V27H21Z\"/><path class=\"ka139-3\" d=\"M21,31h1V30H21Z\"/><path"," class=\"ka139-2\" d=\"M21,30V27H20v6h1V30Z\"/><path class=\"ka139-2\""," d=\"M20,26h1V25H19v1Z\"/><path class=\"ka139-3\" d=\"M17,25V24H12v1Z","\"/><path class=\"ka139-3\" d=\"M9,31H20V30H9Z\"/><path class=\"ka139-","3\" d=\"M9,27v1H20V27H9Z\"/><path class=\"ka139-2\" d=\"M18,25h1V24H17","v1Z\"/><path class=\"ka139-2\" d=\"M16,24h1V23H16Z\"/><path class=\"ka","139-2\" d=\"M13,23H12v1h1Z\"/><path class=\"ka139-2\" d=\"M12,24H10v1h","2Z\"/><path class=\"ka139-2\" d=\"M10,25H8v1h2Z\"/><path class=\"ka139","-2\" d=\"M9,30V27H8v6H9V30Z\"/><rect class=\"ka139-2\" x=\"7\" y=\"26\" w","idth=\"1\" height=\"1\"/><path class=\"ka139-3\" d=\"M7,31H8V30H7Z\"/><p","ath class=\"ka139-3\" d=\"M8,28V27H7v1Z\"/><path class=\"ka139-2\" d=\"","M7,30V27H6v6H7V30Z\"/><path class=\"ka139-4\" d=\"M9,31v2H20V31Z\"/><","path class=\"ka139-4\" d=\"M9,29v1H20V28H9Z\"/><path class=\"ka139-4\""," d=\"M9,27H21V26H19V25H10v1H8v1Z\"/><path class=\"ka139-4\" d=\"M15,2","3H13v1h3V23Z\"/><path class=\"ka139-4\" d=\"M7,29v1H8V28H7Z\"/><path ","class=\"ka139-4\" d=\"M7,31v2H8V31Z\"/><path class=\"ka139-4\" d=\"M21,","31v2h1V31Z\"/><path class=\"ka139-4\" d=\"M21,29v1h1V28H21Z\"/><rect ","class=\"ka139-2\" x=\"20\" y=\"15\" width=\"1\" height=\"1\"/><path class=","\"ka139-2\" d=\"M19,15h1V14H19Z\"/><path class=\"ka139-5\" d=\"M10,17h1","v1h1v1h1V18h5V17h1V16h1V15H16V14h3V13H16V12h2V11H11v1H10v1h3v2H9","v1h1Zm4-1h1v1H14Z\"/><path class=\"ka139-2\" d=\"M10,14H9v1h1Z\"/><re","ct class=\"ka139-2\" x=\"8\" y=\"15\" width=\"1\" height=\"1\"/><rect clas","s=\"ka139-2\" x=\"14\" y=\"16\" width=\"1\" height=\"1\"/><path class=\"ka1","39-6\" d=\"M12,15h1V14H12Z\"/><path class=\"ka139-6\" d=\"M10,14v1h1V1","4Z\"/><path class=\"ka139-6\" d=\"M18,14v1h1V14Z\"/><path class=\"ka13","9-6\" d=\"M16,14v1h1V14Z\"/><path class=\"ka139-2\" d=\"M11,14v1h1V14Z","\"/><path class=\"ka139-2\" d=\"M17,14v1h1V14Z\"/><polygon class=\"ka1","39-7\" points=\"18 12 16 12 16 13 19 13 19 12 18 12\"/><path class=","\"ka139-7\" d=\"M11,14h2V13H10v1Z\"/><path class=\"ka139-8\" d=\"M15,18","H13v1h3V18Z\"/><path class=\"ka139-8\" d=\"M14,23h3V22h1V21h1V20h1V1","6H19v1H18v1H17v1H16v1H13V19H12V18H11V17H10V16H9v4h1v1h1v1h1v1h2Z","\"/><rect class=\"ka139-2\" x=\"13\" y=\"19\" width=\"3\" height=\"1\"/><pa","th class=\"ka139-2\" d=\"M16,19h1V18H16Z\"/><path class=\"ka139-9\" d=","\"M10,13V12h1V11h7v1h1v2h1V13h1V9H20V8H19V7H18V6H11V7H10V8H9V9H8v","4H9v1h1Z\"/></svg>"]}]}