{"name":"CryptoPeep #80","artist":"Benzega","description":"CryptoPeeps is an original pop art NFT collection powered by the Cardano blockchain. Each CryptoPeep is hand-crafted and one-of-a-kind. The artwork source code is stored directly on-chain, guaranteeing permanence and accessibility. Inspired by the likes of CryptoPunks, Spacebudz and Keith Haring, the artist has brought to life an eccentric cohort of pixel peeple to share with the Cardano community. Power to the peeple!","artwork":{"attributes":{"background":"Forest Green","species":"Human","variant":"Normal","clothing":"Collared Shirt","pattern":"Plus Sign","hair":"Crew Cut","facial_hair":"Amish","items":["Flag of Argentina"],"expression":"Grin","eyebrows":"Natural","eyes":"Glance"},"file":{"src":"<svg xmlns=\"http://www.w3.org/2000/svg\" viewBox=\"0 0 29 33\"><defs><style>polygon,rect,path{shape-rendering:crispedges;}.za113-1{fill:#29834f;}.za113-2{fill:#000000;}.za113-3{fill:#00af68;}.za113-4{fill:#ce8452;}.za113-5{fill:#5a2de2;}.za113-6{fill:#ffffff;}.za113-7{fill:#492a23;}.za113-8{fill:#00686d;}.za113-9{fill:#d8be00;}.za113-10{fill:#455054;}.za113-11{fill:#94d4ff;}.za113-12{fill:#e5ac2e;}</style></defs><path class=\"za113-1\" d=\"M8,18v4H9v2H8v1h2V24h1V23h1V21H11V20H10V19H9V16H8v2Z\"/><path class=\"za113-1\" d=\"M8,32H6V31H5V22H6V21H7V20H5v1H2V17H5V16H8V15H9V10h1V9h1V8h7V9h1v1h1v5h1v1H20v3H19v1H18v1H17v2h1v1h1v1h2v1h1v1h1v6h6V0H0V33H8Z\"/><path class=\"za113-2\" d=\"M6,29V22H5v9H6V29Z\"/><path class=\"za113-2\" d=\"M23,27H22v6h1V27Z\"/><path class=\"za113-3\" d=\"M21,30v1h1V29H21Z\"/><path class=\"za113-3\" d=\"M21,32v1h1V32Z\"/><path class=\"za113-3\" d=\"M21,28h1V27H21Z\"/><rect class=\"za113-2\" x=\"21\" y=\"26\" width=\"1\" height=\"1\"/><path class=\"za113-2\" d=\"M21,31V27H20v6h1V31Z\"/><path class=\"za113-3\" d=\"M17,32V31h1V30h1v1h1V29H19V28h1V27h1V26H19v1H18V26H15v1H14V26H11v1H10V26H8v1H9v1h1v1H9v2h1V30h1v1h1v1H11v1h3V32H13V31h1V30h1v1h1v1H15v1h3V32Zm-2-3H13v1H12V29H11V28h1V27h1v1h3V27h1v1h1v1H17v1H16V29Z\"/><path class=\"za113-3\" d=\"M19,32v1h1V32Z\"/><rect class=\"za113-3\" x=\"9\" y=\"32\" width=\"1\" height=\"1\"/><path class=\"za113-2\" d=\"M20,26h1V25H19v1Z\"/><rect class=\"za113-3\" x=\"16\" y=\"24\" width=\"1\" height=\"1\"/><rect class=\"za113-2\" x=\"15\" y=\"24\" width=\"1\" height=\"1\"/><rect class=\"za113-2\" x=\"14\" y=\"32\" width=\"1\" height=\"1\"/><rect class=\"za113-2\" x=\"14\" y=\"30\" width=\"1\" height=\"1\"/><path class=\"za113-2\" d=\"M14,28v1h1V28Z\"/><path class=\"za113-2\" d=\"M14,25v2h1V25Z\"/><rect class=\"za113-2\" x=\"13\" y=\"24\" width=\"1\" height=\"1\"/><path class=\"za113-4\" d=\"M14,24v1h1V24h1V23H13v1Z\"/><rect class=\"za113-3\" x=\"12\" y=\"24\" width=\"1\" height=\"1\"/><path class=\"za113-2\" d=\"M12,25V24h1V22H12v1H11v1H10v1h1v1h2V25Z\"/><path class=\"za113-2\" d=\"M9,31V30H8V26h2V25H8V24H7v7H6v1H8v1H9V31Z\"/><path class=\"za113-3\" d=\"M6,28v2H7V27H6Z\"/><path class=\"za113-5\" d=\"M12,32V31H11V30H10v1H9v1h1v1h1V32Z\"/><path class=\"za113-5\" d=\"M8,30H9V29h1V28H9V27H8v3Z\"/><path class=\"za113-5\" d=\"M7,30H6v1H7Z\"/><path class=\"za113-5\" d=\"M6,25v2H7V24H6Z\"/><path class=\"za113-5\" d=\"M13,28V27H12v1H11v1h1v1h1V29h1V28Z\"/><polygon class=\"za113-5\" points=\"10 25 10 26 10 27 11 27 11 26 11 25 10 25\"/><path class=\"za113-5\" d=\"M13,25v1h1V25Z\"/><path class=\"za113-5\" d=\"M15,25v1h1V25Z\"/><path class=\"za113-5\" d=\"M17,30V29h1V28H17V27H16v1H15v1h1v1Z\"/><polygon class=\"za113-5\" points=\"18 26 18 27 19 27 19 26 19 25 18 25 18 26\"/><path class=\"za113-5\" d=\"M21,29h1V28H21Z\"/><path class=\"za113-5\" d=\"M19,29h1V28H19Z\"/><path class=\"za113-5\" d=\"M21,32h1V31H21Z\"/><polygon class=\"za113-5\" points=\"16 32 16 31 15 31 14 31 13 31 13 32 14 32 15 32 16 32\"/><path class=\"za113-5\" d=\"M20,32V31H19V30H18v1H17v1h1v1h1V32Z\"/><rect class=\"za113-2\" x=\"20\" y=\"15\" width=\"1\" height=\"1\"/><path class=\"za113-2\" d=\"M19,15h1V14H19Z\"/><rect class=\"za113-4\" x=\"16\" y=\"19\" width=\"1\" height=\"1\"/><path class=\"za113-4\" d=\"M10,16v2h1v1h1v1h1V19h3V18h1v1h1V18h1V16h1V15H16V14h2V13H16V12h2V11H17V10H12v1H11v1h1v1h1v2H9v1Zm4,0h1v1H14Z\"/><path class=\"za113-4\" d=\"M14,21h2V20H13v1Z\"/><rect class=\"za113-4\" x=\"18\" y=\"12\" width=\"1\" height=\"1\"/><path class=\"za113-4\" d=\"M10,14h2V13H10Z\"/><path class=\"za113-2\" d=\"M16,23v1h1v1H16v1h2V25h1V24H18V23H17V22H16Z\"/><rect class=\"za113-2\" x=\"8\" y=\"15\" width=\"1\" height=\"1\"/><rect class=\"za113-2\" x=\"14\" y=\"16\" width=\"1\" height=\"1\"/><path class=\"za113-6\" d=\"M18,14v1h1V14Z\"/><path class=\"za113-6\" d=\"M12,15h1V14H12Z\"/><path class=\"za113-2\" d=\"M17,14H16v1h2V14Z\"/><path class=\"za113-2\" d=\"M12,15V14H9v1h3Z\"/><rect class=\"za113-7\" x=\"18\" y=\"13\" width=\"1\" height=\"1\"/><rect class=\"za113-7\" x=\"16\" y=\"12\" width=\"2\" height=\"1\"/><path class=\"za113-7\" d=\"M13,14V13H12v1Z\"/><path class=\"za113-7\" d=\"M10,13h2V12H10Z\"/><path class=\"za113-8\" d=\"M19,17v1H18v1H17v1H16v1H13V20H12V19H11V18H10V16H9v3h1v1h1v1h1v1h1v1h3V22h1V21h1V20h1V19h1V16H19Z\"/><rect class=\"za113-2\" x=\"13\" y=\"19\" width=\"3\" height=\"1\"/><rect class=\"za113-2\" x=\"16\" y=\"18\" width=\"1\" height=\"1\"/><path class=\"za113-9\" d=\"M10,13V12h1V11h1V10h5v1h1v1h1v2h1V10H19V9H18V8H11V9H10v1H9v4h1Z\"/><path class=\"za113-4\" d=\"M7,24H8V22H6v2Z\"/><path class=\"za113-10\" d=\"M8,22V20H7v2Z\"/><path class=\"za113-2\" d=\"M7,21H6v1H7Z\"/><path class=\"za113-2\" d=\"M9,22H8v2H9Z\"/><path class=\"za113-6\" d=\"M4,19V18H2v2H5V19Z\"/><path class=\"za113-6\" d=\"M6,18v1H8V17H5v1Z\"/><path class=\"za113-11\" d=\"M5,18V17H2v1H5Z\"/><path class=\"za113-11\" d=\"M2,20v1H5V20H2Z\"/><path class=\"za113-11\" d=\"M8,17V16H5v1H8Z\"/><path class=\"za113-11\" d=\"M8,19H5v1H8Z\"/><path class=\"za113-12\" d=\"M5,18H4v1H6V18Z\"/></svg>","type":"image/svg+xml"}},"links":{"homepage":"cryptopeeps.io","github":"github.com/cryptopeeps","reddit":"reddit.com/r/cryptopeeps","artist":"benzega.com"}}