{"about":{"name":"CryptoPeep #6077","artist":"Benzega","description":"One-of-a-kind pop art pixel peep living on the blockchain!","links":{"homepage":"https://www.cryptopeeps.io","github":"https://www.github.com/cryptopeeps","reddit":"https://www.reddit.com/r/cryptopeeps","artist":"https://www.benzega.com"},"properties":{"background":"Forest Green","species":"Human","variant":"Normal","clothing":"T-shirt","logo":"IO Global","hair":"Punk","facial_hair":"Goatee","eyewear":"Sunglasses","expression":"Neutral","eyebrows":"Upturned","eyes":"Center"}},"files":[{"preview":"https://cdn.cryptopeeps.io/nft/6077.svg","proximity":"on-chain","media_type":"image/svg+xml","src":["<svg xmlns=\"http://www.w3.org/2000/svg\" viewBox=\"0 0 29 33\"><def","s><style>polygon,rect,path{shape-rendering:crispedges;}.da262-1{","fill:#29834f;}.da262-2{fill:#000000;}.da262-3{fill:#00686d;}.da2","62-4{fill:#b2622b;}.da262-5{fill:#34e0cb;}.da262-6{fill:#663434;","}.da262-7{fill:#663434;}.da262-8{fill:#45ba00;}.da262-9{fill:#ff","ffff;}</style></defs><path class=\"da262-1\" d=\"M0,33H6V27H7V26H8V","25h2V24h2V21H11V20H10V19H9V16H8V14H9V10h1V9h1V8h7V9h1v1h1v4h1v2H","20v3H19v1H18v1H17v3h2v1h2v1h1v1h1v6h6V0H0Z\"/><path class=\"da262-","2\" d=\"M23,27H22v3H21V27H20v6h1V31h1v2h1V27Z\"/><rect class=\"da262","-2\" x=\"21\" y=\"26\" width=\"1\" height=\"1\"/><path class=\"da262-3\" d=","\"M21,28v2h1V27H21Z\"/><path class=\"da262-4\" d=\"M21,31v2h1V31Z\"/><","path class=\"da262-2\" d=\"M20,26h1V25H19v1Z\"/><rect class=\"da262-3","\" x=\"13\" y=\"29\" width=\"1\" height=\"2\"/><path class=\"da262-3\" d=\"M","20,27h1V26H19V25H17v1H16v1H13V26H12V25H10v1H8v1H9v6H20V27Zm-9,2v","3H10V28h1Zm4,3H12V28h3Zm4-3H17v2h1V30h1v2H16V28h3Z\"/><path class","=\"da262-2\" d=\"M18,25h1V24H17v1Z\"/><rect class=\"da262-2\" x=\"16\" y","=\"25\" width=\"1\" height=\"1\"/><path class=\"da262-2\" d=\"M13,26v1h3V","26H13Z\"/><path class=\"da262-2\" d=\"M13,23h3v1h1V21H16v1H13V21H12v","3h1Z\"/><path class=\"da262-4\" d=\"M13,25v1h3V25h1V24H16V23H13v1H12","v1Z\"/><rect class=\"da262-2\" x=\"12\" y=\"25\" width=\"1\" height=\"1\"/>","<path class=\"da262-2\" d=\"M12,24H10v1h2Z\"/><path class=\"da262-2\" ","d=\"M10,25H8v1h2Z\"/><path class=\"da262-2\" d=\"M9,27H8v3H7V27H6v6H7","V31H8v2H9V27Z\"/><rect class=\"da262-2\" x=\"7\" y=\"26\" width=\"1\" hei","ght=\"1\"/><path class=\"da262-3\" d=\"M7,30H8V27H7v3Z\"/><path class=","\"da262-4\" d=\"M7,31v2H8V31Z\"/><path class=\"da262-5\" d=\"M12,32h3V2","8H12Zm1-3h1v2H13Z\"/><path class=\"da262-5\" d=\"M10,29v3h1V28H10Z\"/","><path class=\"da262-5\" d=\"M16,28v4h3V30H18v1H17V29h2V28H16Z\"/><p","ath class=\"da262-2\" d=\"M20,16h1V15H20Z\"/><path class=\"da262-4\" d","=\"M11,12h2v2h2V12H14V11H13V10H11v1H10v2h1Z\"/><rect class=\"da262-","4\" x=\"16\" y=\"19\" width=\"1\" height=\"1\"/><rect class=\"da262-4\" x=\"","13\" y=\"20\" width=\"1\" height=\"1\"/><path class=\"da262-4\" d=\"M12,19","V18h5v1h2V17H16V16H15v1H14V16H13v1H10v2h2Z\"/><rect class=\"da262-","4\" x=\"12\" y=\"19\" width=\"1\" height=\"1\"/><rect class=\"da262-4\" x=\"","14\" y=\"15\" width=\"1\" height=\"1\"/><rect class=\"da262-4\" x=\"15\" y=","\"20\" width=\"1\" height=\"1\"/><path class=\"da262-2\" d=\"M19,17v2h1V1","6H19Z\"/><path class=\"da262-2\" d=\"M18,20h1V19H18Z\"/><rect class=\"","da262-2\" x=\"17\" y=\"20\" width=\"1\" height=\"1\"/><rect class=\"da262-","2\" x=\"11\" y=\"20\" width=\"1\" height=\"1\"/><path class=\"da262-2\" d=\"","M10,19v1h1V19Z\"/><path class=\"da262-2\" d=\"M10,16H9v3h1V16Z\"/><pa","th class=\"da262-2\" d=\"M8,15v1H9V15Z\"/><rect class=\"da262-2\" x=\"1","4\" y=\"16\" width=\"1\" height=\"1\"/><path class=\"da262-6\" d=\"M11,12v","1h2V12Z\"/><path class=\"da262-7\" d=\"M17,19v1h1V19Z\"/><rect class=","\"da262-7\" x=\"16\" y=\"20\" width=\"1\" height=\"1\"/><path class=\"da262","-7\" d=\"M15,20H14v1H13v1h3V21H15Z\"/><path class=\"da262-7\" d=\"M14,","19h3V18H12v1h2Z\"/><rect class=\"da262-7\" x=\"12\" y=\"20\" width=\"1\" ","height=\"1\"/><path class=\"da262-7\" d=\"M12,19H11v1h1Z\"/><path clas","s=\"da262-2\" d=\"M15,20h1V19H13v1h2Z\"/><path class=\"da262-8\" d=\"M1","0,13V11h1V10h2v1h1v1h1v2h1V13h3v1h1V10H19V9H18V8H11V9H10v1H9v4h1","Z\"/><path class=\"da262-9\" d=\"M19,15v1h1V15h1V14H19Z\"/><path clas","s=\"da262-9\" d=\"M19,14V13H16v1h3Z\"/><path class=\"da262-2\" d=\"M19,","16V14H16v2h3Z\"/><path class=\"da262-9\" d=\"M18,16H16v1h3V16Z\"/><pa","th class=\"da262-9\" d=\"M15,14H13v2h1V15h1v1h1V14Z\"/><path class=\"","da262-9\" d=\"M13,14V13H10v1h3Z\"/><path class=\"da262-2\" d=\"M12,14H","10v2h3V14Z\"/><path class=\"da262-9\" d=\"M10,16v1h3V16H10Z\"/><path ","class=\"da262-9\" d=\"M10,15V14H8v1H9v1h1Z\"/></svg>"]}]}