{"about":{"name":"CryptoPeep #2334","artist":"Benzega","description":"One-of-a-kind pop art pixel peep living on the blockchain!","links":{"homepage":"cryptopeeps.io","github":"github.com/cryptopeeps","reddit":"reddit.com/r/cryptopeeps","artist":"benzega.com"},"properties":{"background":"Forest Green","species":"Human","variant":"Normal","clothing":"T-shirt","logo":"IO Global","hair":"Geyser","facial_hair":"Handlebar Mustache","expression":"Grin","eyebrows":"Natural","eyes":"Center"}},"files":[{"proximity":"on-chain","media_type":"image/svg+xml","src":{"chunks":{"1":"<svg xmlns=\"http://www.w3.org/2000/svg\" viewBox=\"0 0 29 33\"><def","2":"s><style>polygon,rect,path{shape-rendering:crispedges;}.da208-1{","3":"fill:#29834f;}.da208-2{fill:#000000;}.da208-3{fill:#6d5800;}.da2","4":"08-4{fill:#a56e49;}.da208-5{fill:#d8be00;}.da208-6{fill:#ffffff;","5":"}.da208-7{fill:#492a23;}.da208-8{fill:#492a23;}.da208-9{fill:#ff","6":"1d99;}</style></defs><path class=\"da208-1\" d=\"M0,33H6V27H7V26H8V","7":"25h2V24h2V21H11V20H10V19H9V16H8V15H9V11h1V10h1V9h2V7h1V6h2V5h2V6","8":"H17V7h1V9h1v2h1v4h1v1H20v3H19v1H18v1H17v3h2v1h2v1h1v1h1v6h6V0H0Z","9":"\"/><path class=\"da208-2\" d=\"M23,27H22v3H21V27H20v6h1V31h1v2h1V27","10":"Z\"/><rect class=\"da208-2\" x=\"21\" y=\"26\" width=\"1\" height=\"1\"/><p","11":"ath class=\"da208-3\" d=\"M21,28v2h1V27H21Z\"/><path class=\"da208-4\"","12":" d=\"M21,31v2h1V31Z\"/><path class=\"da208-2\" d=\"M20,26h1V25H19v1Z\"","13":"/><rect class=\"da208-3\" x=\"13\" y=\"29\" width=\"1\" height=\"2\"/><pat","14":"h class=\"da208-3\" d=\"M20,27h1V26H19V25H17v1H16v1H13V26H12V25H10v","15":"1H8v1H9v6H20V27Zm-9,2v3H10V28h1Zm4,3H12V28h3Zm4-3H17v2h1V30h1v2H","16":"16V28h3Z\"/><path class=\"da208-2\" d=\"M18,25h1V24H17v1Z\"/><rect cl","17":"ass=\"da208-2\" x=\"16\" y=\"25\" width=\"1\" height=\"1\"/><path class=\"d","18":"a208-2\" d=\"M13,26v1h3V26H13Z\"/><path class=\"da208-2\" d=\"M13,23h3","19":"v1h1V21H16v1H13V21H12v3h1Z\"/><path class=\"da208-4\" d=\"M13,25v1h3","20":"V25h1V24H16V23H13v1H12v1Z\"/><rect class=\"da208-2\" x=\"12\" y=\"25\" ","21":"width=\"1\" height=\"1\"/><path class=\"da208-2\" d=\"M12,24H10v1h2Z\"/>","22":"<path class=\"da208-2\" d=\"M10,25H8v1h2Z\"/><path class=\"da208-2\" d","23":"=\"M9,27H8v3H7V27H6v6H7V31H8v2H9V27Z\"/><rect class=\"da208-2\" x=\"7","24":"\" y=\"26\" width=\"1\" height=\"1\"/><path class=\"da208-3\" d=\"M7,30H8V","25":"27H7v3Z\"/><path class=\"da208-4\" d=\"M7,31v2H8V31Z\"/><path class=\"","26":"da208-5\" d=\"M12,32h3V28H12Zm1-3h1v2H13Z\"/><path class=\"da208-5\" ","27":"d=\"M10,29v3h1V28H10Z\"/><path class=\"da208-5\" d=\"M16,28v4h3V30H18","28":"v1H17V29h2V28H16Z\"/><rect class=\"da208-2\" x=\"20\" y=\"15\" width=\"1","29":"\" height=\"1\"/><path class=\"da208-2\" d=\"M19,13v2h1V11H19v2Z\"/><pa","30":"th class=\"da208-4\" d=\"M12,19V18h5v2h1V19h1V16h1V15H16V13h1V12h2V","31":"11H18V10H15v1H13V10H11v1H10v2h1V12h2v1H11v1h2v1H9v1h1v3h1v1h1Zm2","32":"-3h1v1H14Z\"/><path class=\"da208-4\" d=\"M13,20v2h3V20Z\"/><path cla","33":"ss=\"da208-4\" d=\"M18,14h1V13H17v1Z\"/><path class=\"da208-2\" d=\"M19","34":",17v2h1V16H19Z\"/><path class=\"da208-2\" d=\"M18,11h1V10H18Z\"/><rec","35":"t class=\"da208-2\" x=\"18\" y=\"19\" width=\"1\" height=\"1\"/><rect clas","36":"s=\"da208-2\" x=\"17\" y=\"20\" width=\"1\" height=\"1\"/><path class=\"da2","37":"08-2\" d=\"M16,10h2V9H16Z\"/><path class=\"da208-2\" d=\"M13,9H11v1h2Z","38":"\"/><rect class=\"da208-2\" x=\"11\" y=\"20\" width=\"1\" height=\"1\"/><re","39":"ct class=\"da208-2\" x=\"10\" y=\"10\" width=\"1\" height=\"1\"/><rect cla","40":"ss=\"da208-2\" x=\"10\" y=\"19\" width=\"1\" height=\"1\"/><path class=\"da","41":"208-2\" d=\"M10,14V11H9v4h1Z\"/><path class=\"da208-2\" d=\"M10,16H9v3","42":"h1V16Z\"/><rect class=\"da208-2\" x=\"8\" y=\"15\" width=\"1\" height=\"1\"","43":"/><rect class=\"da208-2\" x=\"14\" y=\"16\" width=\"1\" height=\"1\"/><pat","44":"h class=\"da208-6\" d=\"M13,15V14H12v1Z\"/><path class=\"da208-6\" d=\"","45":"M10,15h1V14H10Z\"/><path class=\"da208-6\" d=\"M18,14v1h1V14Z\"/><pat","46":"h class=\"da208-6\" d=\"M16,14v1h1V14Z\"/><path class=\"da208-2\" d=\"M","47":"12,15V14H11v1Z\"/><path class=\"da208-2\" d=\"M17,14v1h1V14Z\"/><path","48":" class=\"da208-7\" d=\"M11,14V13H10v1Z\"/><rect class=\"da208-7\" x=\"1","49":"1\" y=\"12\" width=\"2\" height=\"1\"/><path class=\"da208-7\" d=\"M17,13H","50":"16v1h1Z\"/><path class=\"da208-7\" d=\"M19,12H17v1h2Z\"/><path class=","51":"\"da208-8\" d=\"M17,19V18H13v1h3v2h1V19Z\"/><path class=\"da208-8\" d=","52":"\"M13,20V19H12v2h1Z\"/><path class=\"da208-2\" d=\"M16,19H13v1h3Z\"/><","53":"path class=\"da208-2\" d=\"M12,18v1h1V18Z\"/><path class=\"da208-9\" d","54":"=\"M13,11h2V10h1V9h2V7H17V6h1V5H16V6H14V7H13v4Z\"/><path class=\"da","55":"208-9\" d=\"M19,10V9H18v1Z\"/><rect class=\"da208-9\" x=\"18\" y=\"9\" wi","56":"dth=\"1\" height=\"1\"></rect></svg>"}}}]}