{"about":{"name":"CryptoPeep #3631","artist":"Benzega","description":"One-of-a-kind pop art pixel peep living on the blockchain!","links":{"homepage":"cryptopeeps.io","github":"github.com/cryptopeeps","reddit":"reddit.com/r/cryptopeeps","artist":"benzega.com"},"properties":{"background":"Blue","species":"Human","variant":"Normal","clothing":"Sweatshirt","pattern":"Plus Sign","hair":"Geyser","facial_hair":"Lumberjack","eyewear":"Square Glasses","jewelry":"Diamond Necklace","expression":"Grin","eyebrows":"Natural","eyes":"Center"}},"files":[{"proximity":"on-chain","media_type":"image/svg+xml","src":{"chunks":{"0":"<svg xmlns=\"http://www.w3.org/2000/svg\" viewBox=\"0 0 29 33\"><def","1":"s><style>polygon,rect,path{shape-rendering:crispedges;}.na258-1{","2":"fill:#397d98;}.na258-2{fill:#000000;}.na258-3{fill:#560000;}.na2","3":"58-4{fill:#6c9302;}.na258-5{fill:#b2622b;}.na258-6{fill:#cc3232;","4":"}.na258-7{fill:#663228;}.na258-8{fill:#fad000;}.na258-9{fill:#ff","5":"ffff;}.na258-10{fill:#663228;}.na258-11{fill:#ff791f;}.na258-12{","6":"fill:#68aaad;}</style></defs><path class=\"na258-1\" d=\"M0,33H6V27","7":"H7V26H8V25h2V23h1V21H10V20H9V16H8V15H9V11h1V10h1V7h1V6H11V5h2V6h","8":"2V7h1V9h2v1h1v1h1v4h1v1H20v4H19v1H18v2h1v2h2v1h1v1h1v6h6V0H0Z\"/>","9":"<path class=\"na258-2\" d=\"M23,27H22v6h1V27Z\"/><rect class=\"na258-","10":"2\" x=\"21\" y=\"26\" width=\"1\" height=\"1\"/><path class=\"na258-3\" d=\"","11":"M21,30v1h1V29H21Z\"/><path class=\"na258-3\" d=\"M21,28h1V27H21Z\"/><","12":"path class=\"na258-3\" d=\"M21,32v1h1V32Z\"/><path class=\"na258-2\" d","13":"=\"M21,31V27H20v6h1V31Z\"/><path class=\"na258-3\" d=\"M19,26v1H18v3h","14":"1v1h1V29H19V28h1V27h1V26H19Z\"/><path class=\"na258-3\" d=\"M19,32v1","15":"h1V32Z\"/><path class=\"na258-2\" d=\"M20,26h1V25H19v1Z\"/><path clas","16":"s=\"na258-2\" d=\"M18,30V25H17v1H16v1h1v6h1V30Z\"/><path class=\"na25","17":"8-4\" d=\"M17,27H16v1H13V27H12v6h5V27Z\"/><path class=\"na258-5\" d=\"","18":"M13,25h3V23H13v2Z\"/><path class=\"na258-2\" d=\"M12,27h1V26H12V25H1","19":"1v8h1V27Z\"/><rect class=\"na258-3\" x=\"9\" y=\"32\" width=\"1\" height=","20":"\"1\"/><path class=\"na258-3\" d=\"M9,27v1h1v1H9v2h1V30h1V27H10V26H8v","21":"1Z\"/><path class=\"na258-2\" d=\"M10,25H8v1h2Z\"/><path class=\"na258","22":"-2\" d=\"M9,31V27H8v6H9V31Z\"/><rect class=\"na258-2\" x=\"7\" y=\"26\" w","23":"idth=\"1\" height=\"1\"/><path class=\"na258-3\" d=\"M7,32v1H8V32Z\"/><p","24":"ath class=\"na258-3\" d=\"M7,30v1H8V29H7Z\"/><path class=\"na258-3\" d","25":"=\"M8,28V27H7v1Z\"/><path class=\"na258-2\" d=\"M7,31V27H6v6H7V31Z\"/>","26":"<path class=\"na258-6\" d=\"M11,30H10v1H9v1h1v1h1V30Z\"/><path class","27":"=\"na258-6\" d=\"M10,27h1V25H10v2Z\"/><path class=\"na258-6\" d=\"M18,2","28":"6v1h1V25H18Z\"/><path class=\"na258-6\" d=\"M7,29H8V28H7Z\"/><path cl","29":"ass=\"na258-6\" d=\"M10,28H9v1h1Z\"/><path class=\"na258-6\" d=\"M21,29","30":"h1V28H21Z\"/><path class=\"na258-6\" d=\"M19,29h1V28H19Z\"/><path cla","31":"ss=\"na258-6\" d=\"M21,32h1V31H21Z\"/><path class=\"na258-6\" d=\"M7,32","32":"H8V31H7Z\"/><path class=\"na258-6\" d=\"M20,32V31H19V30H18v3h1V32Z\"/","33":"><rect class=\"na258-2\" x=\"20\" y=\"15\" width=\"1\" height=\"1\"/><path","34":" class=\"na258-2\" d=\"M18,13H15v1h4v1h1V11H19v2Z\"/><path class=\"na","35":"258-5\" d=\"M16,16V15H13v1H10v1h1v1h1v1h1V18h5V17h1V16H16Zm-1,1H14","36":"V16h1Z\"/><rect class=\"na258-5\" x=\"9\" y=\"15\" width=\"1\" height=\"1\"","37":"/><rect class=\"na258-5\" x=\"19\" y=\"15\" width=\"1\" height=\"1\"/><pat","38":"h class=\"na258-5\" d=\"M12,12v1h2v1h1V13h1V12h2v1h1V11H18V10H16v1H","39":"14V10H11v1H10v1Z\"/><rect class=\"na258-2\" x=\"18\" y=\"10\" width=\"1\"","40":" height=\"1\"/><path class=\"na258-2\" d=\"M17,10h1V9H16v1Z\"/><path c","41":"lass=\"na258-2\" d=\"M13,9H11v1h2Z\"/><rect class=\"na258-2\" x=\"10\" y","42":"=\"10\" width=\"1\" height=\"1\"/><rect class=\"na258-2\" x=\"8\" y=\"15\" w","43":"idth=\"1\" height=\"1\"/><rect class=\"na258-2\" x=\"14\" y=\"16\" width=\"","44":"1\" height=\"1\"/><path class=\"na258-7\" d=\"M18,12H16v1h2Z\"/><path c","45":"lass=\"na258-7\" d=\"M10,12v1h2V12Z\"/><path class=\"na258-2\" d=\"M18,","46":"25h1V23H18v2Z\"/><path class=\"na258-8\" d=\"M17,24v1h1V24Z\"/><path ","47":"class=\"na258-9\" d=\"M17,24h1V23H17Z\"/><path class=\"na258-2\" d=\"M1","48":"7,23h1V22H17Z\"/><rect class=\"na258-9\" x=\"16\" y=\"25\" width=\"1\" he","49":"ight=\"1\"/><path class=\"na258-2\" d=\"M17,23H16v2h1V23Z\"/><rect cla","50":"ss=\"na258-8\" x=\"15\" y=\"26\" width=\"1\" height=\"1\"/><path class=\"na","51":"258-2\" d=\"M14,27H13v1h3V27H14Z\"/><path class=\"na258-9\" d=\"M15,27","52":"V26H14v1Z\"/><rect class=\"na258-8\" x=\"13\" y=\"26\" width=\"1\" height","53":"=\"1\"/><path class=\"na258-2\" d=\"M15,25H13v1h3V25Z\"/><rect class=\"","54":"na258-9\" x=\"12\" y=\"25\" width=\"1\" height=\"1\"/><path class=\"na258-","55":"2\" d=\"M13,24V23H12v2h1Z\"/><path class=\"na258-8\" d=\"M11,24v1h1V24","56":"Z\"/><path class=\"na258-9\" d=\"M12,24V23H11v1Z\"/><path class=\"na25","57":"8-2\" d=\"M12,22H11v1h1Z\"/><path class=\"na258-2\" d=\"M11,24V23H10v2","58":"h1Z\"/><path class=\"na258-10\" d=\"M15,18H13v1h3V18Z\"/><path class=","59":"\"na258-10\" d=\"M12,23h5V22h1V21h1V20h1V16H19v1H18v1H17v1H16v1H13V","60":"19H12V18H11V17H10V16H9v4h1v1h1v1h1Z\"/><rect class=\"na258-2\" x=\"1","61":"3\" y=\"19\" width=\"3\" height=\"1\"/><path class=\"na258-2\" d=\"M16,19h","62":"1V18H16Z\"/><path class=\"na258-11\" d=\"M13,10h1v1h2V7H15V6H13V5H11","63":"V6h1V7H11V9h2Z\"/><path class=\"na258-12\" d=\"M13,16V15h1V14H10v2h3","64":"Z\"/><path class=\"na258-12\" d=\"M19,14H15v1h1v1h3V14Z\"/><path clas","65":"s=\"na258-2\" d=\"M10,14h4V13H10V11H9v4h1Z\"/><path class=\"na258-2\" ","66":"d=\"M15,15V14H14v1Z\"/><rect class=\"na258-11\" x=\"10\" y=\"9\" width=\"","67":"1\" height=\"1\"></rect></svg>"}}}]}