{"name":"CryptoPeep #844","artist":"Benzega","description":"One-of-a-kind pop art pixel peep living on the blockchain!","homepage":"https://www.cryptopeeps.io","Properties":{"Background":"Yellow","Species":"Human","Variant":"Normal","Clothing":"Turtleneck","Pattern":"Stripes","Hair":"Emo","Facial Hair":"Handlebar Mustache","Expression":"Grin","Eyebrows":"Natural","Eyes":"Center"},"image":["data:image/svg+xml;utf8,%3Csvg xmlns='http://www.w3.org/2000/svg","' xmlns:xlink='http://www.w3.org/1999/xlink' viewBox='0 0 29 33'","%3E%3Cdefs%3E%3Cstyle%3Epolygon,rect,path%7Bshape-rendering:cris","pedges;%7D.ja117-1%7Bfill:%23d4a122;%7D.ja117-2%7Bfill:%23000000",";%7D.ja117-3%7Bfill:%233e5e00;%7D.ja117-4%7Bfill:%2300e070;%7D.j","a117-5%7Bfill:%23ce8452;%7D.ja117-6%7Bfill:%23ffffff;%7D.ja117-7","%7Bfill:%2366334f;%7D.ja117-8%7Bfill:%235e362f;%7D.ja117-9%7Bfil","l:%23db5800;%7D%3C/style%3E%3C/defs%3E%3Cpath class='ja117-1' d=","'M0,33H6V27H7V26H8V25h2V24h2V21H11V20H10V19H9V16H8V15H9V11h1V10h","1V9h7v1h1v1h1v4h1v1H20v3H19v1H18v1H17v3h2v1h2v1h1v1h1v6h6V0H0Z'/","%3E%3Cpath class='ja117-2' d='M23,27H22v6h1V27Z'/%3E%3Crect clas","s='ja117-2' x='21' y='26' width='1' height='1'/%3E%3Cpath class=","'ja117-3' d='M21,31h1V30H21Z'/%3E%3Cpath class='ja117-3' d='M21,","28h1V27H21Z'/%3E%3Cpath class='ja117-2' d='M21,30V27H20v6h1V30Z'","/%3E%3Cpath class='ja117-2' d='M20,26h1V25H19v1Z'/%3E%3Cpath cla","ss='ja117-3' d='M9,31H20V30H9Z'/%3E%3Cpath class='ja117-3' d='M9",",27v1H20V27H9Z'/%3E%3Cpath class='ja117-3' d='M17,25V24H12v1Z'/%","3E%3Cpath class='ja117-2' d='M18,25h1V24H17v1Z'/%3E%3Cpath class","='ja117-2' d='M13,23h3v1h1V21H16v1H13V21H12v3h1Z'/%3E%3Cpath cla","ss='ja117-2' d='M12,24H10v1h2Z'/%3E%3Cpath class='ja117-2' d='M1","0,25H8v1h2Z'/%3E%3Cpath class='ja117-2' d='M9,30V27H8v6H9V30Z'/%","3E%3Crect class='ja117-2' x='7' y='26' width='1' height='1'/%3E%","3Cpath class='ja117-3' d='M8,28V27H7v1Z'/%3E%3Cpath class='ja117","-3' d='M7,31H8V30H7Z'/%3E%3Cpath class='ja117-2' d='M7,30V27H6v6","H7V30Z'/%3E%3Cpath class='ja117-4' d='M9,31v2H20V31Z'/%3E%3Cpath"," class='ja117-4' d='M9,29v1H20V28H9Z'/%3E%3Cpath class='ja117-4'"," d='M9,27H21V26H19V25H10v1H8v1Z'/%3E%3Cpath class='ja117-4' d='M","15,23H13v1h3V23Z'/%3E%3Cpath class='ja117-4' d='M7,29v1H8V28H7Z'","/%3E%3Cpath class='ja117-4' d='M7,31v2H8V31Z'/%3E%3Cpath class='","ja117-4' d='M21,31v2h1V31Z'/%3E%3Cpath class='ja117-4' d='M21,29","v1h1V28H21Z'/%3E%3Crect class='ja117-2' x='20' y='15' width='1' ","height='1'/%3E%3Crect class='ja117-5' x='19' y='15' width='1' he","ight='1'/%3E%3Cpath class='ja117-5' d='M12,19V18h5v2h1V19h1V17H1","8V16H16V15H15v2H14V15H9v1h1v3h1v1h1Z'/%3E%3Cpath class='ja117-5'"," d='M13,20v2h3V20Z'/%3E%3Cpath class='ja117-2' d='M19,17v2h1V16H","19Z'/%3E%3Crect class='ja117-2' x='18' y='19' width='1' height='","1'/%3E%3Crect class='ja117-2' x='17' y='20' width='1' height='1'","/%3E%3Crect class='ja117-2' x='11' y='20' width='1' height='1'/%","3E%3Crect class='ja117-2' x='10' y='19' width='1' height='1'/%3E","%3Cpath class='ja117-2' d='M10,16H9v3h1V16Z'/%3E%3Crect class='j","a117-2' x='8' y='15' width='1' height='1'/%3E%3Cpath class='ja11","7-2' d='M14,17h1V16H14Z'/%3E%3Cpath class='ja117-6' d='M12,14v1h","1V14Z'/%3E%3Cpath class='ja117-6' d='M10,14v1h1V14Z'/%3E%3Cpath ","class='ja117-2' d='M11,14v1h1V14Z'/%3E%3Crect class='ja117-7' x=","'12' y='13' width='1' height='1'/%3E%3Cpath class='ja117-8' d='M","17,19H16v2h1V19Z'/%3E%3Cpath class='ja117-8' d='M13,20V19h3V18H1","2v3h1Z'/%3E%3Cpath class='ja117-2' d='M16,19H13v1h3Z'/%3E%3Cpath"," class='ja117-2' d='M17,18H16v1h1Z'/%3E%3Cpath class='ja117-9' d","='M10,14h2V13h1v2h1v1h1V15h1v1h2v1h1V15h1V11H19V10H18V9H11v1H10v","1H9v4h1Z'/%3E%3C/svg%3E"],"mediaType":"image/svg+xml"}